mg_thumbor/__init__.py
mg_thumbor/filters/__init__.py
mg_thumbor/filters/clip.py
mg_thumbor-0.2.0.dist-info/DESCRIPTION.rst
mg_thumbor-0.2.0.dist-info/METADATA
mg_thumbor-0.2.0.dist-info/RECORD
mg_thumbor-0.2.0.dist-info/WHEEL
mg_thumbor-0.2.0.dist-info/metadata.json
mg_thumbor-0.2.0.dist-info/top_level.txt
